forloop/__init__.py
forloop/forloop_core.py
forloop-0.1.0.dist-info/LICENSE
forloop-0.1.0.dist-info/METADATA
forloop-0.1.0.dist-info/WHEEL
forloop-0.1.0.dist-info/top_level.txt
forloop-0.1.0.dist-info/RECORD
