Metadata-Version: 2.1
Name: forloop
Version: 0.1.0
Summary: Forloop.ai platform - package containing public API commands
Home-page: https://github.com/ForloopAI/forloop
Author: DovaX
Author-email: dominik@forloop.ai
License: UNKNOWN
Platform: UNKNOWN
Classifier: Programming Language :: Python :: 3
Classifier: License :: OSI Approved :: MIT License
Classifier: Operating System :: OS Independent
Requires-Python: >=3.6
